auth0/__init__.py
auth0/v2/__init__.py
auth0/v2/exceptions.py
auth0/v2/authentication/__init__.py
auth0/v2/authentication/base.py
auth0/v2/authentication/database.py
auth0/v2/authentication/delegated.py
auth0/v2/authentication/enterprise.py
auth0/v2/authentication/link.py
auth0/v2/authentication/oauth.py
auth0/v2/authentication/passwordless.py
auth0/v2/authentication/social.py
auth0/v2/authentication/users.py
auth0/v2/management/__init__.py
auth0/v2/management/auth0.py
auth0/v2/management/blacklists.py
auth0/v2/management/clients.py
auth0/v2/management/connections.py
auth0/v2/management/device_credentials.py
auth0/v2/management/emails.py
auth0/v2/management/jobs.py
auth0/v2/management/rest.py
auth0/v2/management/rules.py
auth0/v2/management/stats.py
auth0/v2/management/tenants.py
auth0/v2/management/tickets.py
auth0/v2/management/users.py
auth0/v2/test/__init__.py
auth0/v2/test/authentication/__init__.py
auth0/v2/test/authentication/test_base.py
auth0/v2/test/authentication/test_database.py
auth0/v2/test/authentication/test_delegated.py
auth0/v2/test/authentication/test_enterprise.py
auth0/v2/test/authentication/test_link.py
auth0/v2/test/authentication/test_passwordless.py
auth0/v2/test/authentication/test_social.py
auth0/v2/test/authentication/test_users.py
auth0/v2/test/management/__init__.py
auth0/v2/test/management/test_blacklists.py
auth0/v2/test/management/test_clients.py
auth0/v2/test/management/test_connections.py
auth0/v2/test/management/test_device_credentials.py
auth0/v2/test/management/test_emails.py
auth0/v2/test/management/test_jobs.py
auth0/v2/test/management/test_rest.py
auth0/v2/test/management/test_rules.py
auth0/v2/test/management/test_stats.py
auth0/v2/test/management/test_tenants.py
auth0/v2/test/management/test_tickets.py
auth0/v2/test/management/test_users.py
setec_auth0_python-2.0.1.dist-info/LICENSE
setec_auth0_python-2.0.1.dist-info/METADATA
setec_auth0_python-2.0.1.dist-info/WHEEL
setec_auth0_python-2.0.1.dist-info/top_level.txt
setec_auth0_python-2.0.1.dist-info/RECORD
