Metadata-Version: 2.1
Name: setec-auth0-python
Version: 2.0.1
Summary: Fork of the Auth0 Python SDK
Home-page: https://github.com/auth0/auth0-python
Author: Auth0
Author-email: support@auth0.com
License: MIT
Platform: UNKNOWN
Classifier: Development Status :: 4 - Beta
Classifier: Intended Audience :: Developers
Classifier: Operating System :: OS Independent
Classifier: License :: OSI Approved :: MIT License
Classifier: Programming Language :: Python :: 2.7
Classifier: Programming Language :: Python :: 3
Classifier: Programming Language :: Python :: 3.2
Classifier: Programming Language :: Python :: 3.3
Classifier: Programming Language :: Python :: 3.4
Classifier: Programming Language :: Python :: 3.5
Requires-Dist: requests
Provides-Extra: test
Requires-Dist: mock ; extra == 'test'
